django_pg_jsonschema/.gitkeep
django_pg_jsonschema/__init__.py
django_pg_jsonschema/apps.py
django_pg_jsonschema/configuration.py
django_pg_jsonschema/fields.py
django_pg_jsonschema/signals.py
django_pg_jsonschema/sql.py
django_pg_jsonschema-0.1.2.dist-info/LICENSE
django_pg_jsonschema-0.1.2.dist-info/METADATA
django_pg_jsonschema-0.1.2.dist-info/WHEEL
django_pg_jsonschema-0.1.2.dist-info/RECORD
