Metadata-Version: 2.1
Name: django-pg-jsonschema
Version: 0.1.2
Summary: Django-implementation for PostgreSQL JSONSchema
License: Apache 2.0
Author: Max Boone
Author-email: m.boone@liacs.leidenuniv.nl
Requires-Python: >=3.8,<4.0
Classifier: License :: Other/Proprietary License
Classifier: Programming Language :: Python :: 3
Classifier: Programming Language :: Python :: 3.8
Classifier: Programming Language :: Python :: 3.9
Classifier: Programming Language :: Python :: 3.10
Classifier: Programming Language :: Python :: 3.11
Requires-Dist: django (>=3.2,<4.3)
Requires-Dist: jsonschema (>=4.17.3,<5.0.0)
